md2pdf/__init__.py
md2pdf/cli.py
md2pdf/converter.py
md2pdf/emoji_handler.py
md2pdf/html_renderer.py
md2pdf/mermaid.py
md2pdf_mermaid-1.4.3.dist-info/METADATA
md2pdf_mermaid-1.4.3.dist-info/WHEEL
md2pdf_mermaid-1.4.3.dist-info/entry_points.txt
md2pdf_mermaid-1.4.3.dist-info/top_level.txt
md2pdf_mermaid-1.4.3.dist-info/RECORD
