Metadata-Version: 2.4
Name: md2pdf-mermaid
Version: 1.4.3
Summary: Convert Markdown to PDF with Mermaid diagram rendering and emoji support
Home-page: https://github.com/rbutinar/md2pdf-mermaid
Author: Roberto Butinar
Author-email: Roberto Butinar <roberto.butinar@gmail.com>
License: MIT
Project-URL: Homepage, https://github.com/rbutinar/md2pdf-mermaid
Project-URL: Repository, https://github.com/rbutinar/md2pdf-mermaid
Project-URL: Issues, https://github.com/rbutinar/md2pdf-mermaid/issues
Keywords: markdown,pdf,mermaid,diagram,converter,documentation
Classifier: Development Status :: 4 - Beta
Classifier: Intended Audience :: Developers
Classifier: Topic :: Documentation
Classifier: Topic :: Text Processing :: Markup
Classifier: License :: OSI Approved :: MIT License
Classifier: Programming Language :: Python :: 3
Classifier: Programming Language :: Python :: 3.8
Classifier: Programming Language :: Python :: 3.9
Classifier: Programming Language :: Python :: 3.10
Classifier: Programming Language :: Python :: 3.11
Classifier: Programming Language :: Python :: 3.12
Classifier: Operating System :: OS Independent
Requires-Python: >=3.8
Requires-Dist: reportlab>=4.0.0
Requires-Dist: playwright>=1.40.0
Requires-Dist: pillow>=10.0.0
Requires-Dist: markdown>=3.0.0
Provides-Extra: emoji
Requires-Dist: pilmoji>=2.0.0; extra == "emoji"
Provides-Extra: dev
Requires-Dist: pytest>=7.0; extra == "dev"
Requires-Dist: pytest-cov>=4.0; extra == "dev"
Requires-Dist: black>=23.0; extra == "dev"
Requires-Dist: flake8>=6.0; extra == "dev"
Requires-Dist: mypy>=1.0; extra == "dev"
Dynamic: author
Dynamic: home-page
Dynamic: requires-python
